ai_data_preprocessing_queue/Pipeline.py
ai_data_preprocessing_queue/StepProcessor.py
ai_data_preprocessing_queue/__init__.py
ai_data_preprocessing_queue/Steps/__init__.py
ai_data_preprocessing_queue/Steps/language_detect.py
ai_data_preprocessing_queue/Steps/regex_replacement.py
ai_data_preprocessing_queue/Steps/remove_numbers.py
ai_data_preprocessing_queue/Steps/remove_punctuation.py
ai_data_preprocessing_queue/Steps/snowball_stemmer.py
ai_data_preprocessing_queue/Steps/spellcheck.py
ai_data_preprocessing_queue/Steps/text_only.py
ai_data_preprocessing_queue/Steps/to_lower.py
ai_data_preprocessing_queue/Steps/token_replacement.py
ai_data_preprocessing_queue-1.5.0.dist-info/LICENSE.txt
ai_data_preprocessing_queue-1.5.0.dist-info/METADATA
ai_data_preprocessing_queue-1.5.0.dist-info/WHEEL
ai_data_preprocessing_queue-1.5.0.dist-info/top_level.txt
ai_data_preprocessing_queue-1.5.0.dist-info/RECORD
