Metadata-Version: 2.1
Name: ai-data-preprocessing-queue
Version: 1.5.0
Summary: Can be used to pre process data before ai processing
Home-page: https://github.com/SamhammerAG/ai_data_preprocessing_queue
Author: Samhammer AG
Author-email: support@samhammer.de
License: MIT
Project-URL: Documentation, https://github.com/SamhammerAG/ai_data_preprocessing_queue
Project-URL: Bug Reports, https://github.com/SamhammerAG/ai_data_preprocessing_queue/issues
Project-URL: Source, https://github.com/SamhammerAG/ai_data_preprocessing_queue
Keywords: text processing,ai
Classifier: Programming Language :: Python :: 3
Classifier: License :: OSI Approved :: MIT License
Classifier: Operating System :: OS Independent
Classifier: Topic :: Software Development :: Libraries :: Python Modules
Classifier: Topic :: Software Development :: Libraries
Classifier: Topic :: Software Development
Requires-Python: >=3.12
License-File: LICENSE.txt
Requires-Dist: langdetect ~=1.0.9
Requires-Dist: nltk >=3.7
Requires-Dist: pandas >=1.5.1
Requires-Dist: numpy >=1.23.4
Provides-Extra: dev
Requires-Dist: flake8-bandit ; extra == 'dev'
Requires-Dist: flake8-pydocstyle ; extra == 'dev'
Requires-Dist: mypy ; extra == 'dev'
Requires-Dist: build ; extra == 'dev'
Requires-Dist: pytest ; extra == 'dev'
Requires-Dist: pytest-asyncio ; extra == 'dev'
Requires-Dist: pytest-cov ; extra == 'dev'
Requires-Dist: coverage-lcov ; extra == 'dev'
Requires-Dist: mock ; extra == 'dev'
Requires-Dist: types-mock ; extra == 'dev'
